topsis/__init__.py
topsis/__main__.py
Topsis_Amrendra_101903414-1.0.0.dist-info/LICENSE
Topsis_Amrendra_101903414-1.0.0.dist-info/METADATA
Topsis_Amrendra_101903414-1.0.0.dist-info/WHEEL
Topsis_Amrendra_101903414-1.0.0.dist-info/top_level.txt
Topsis_Amrendra_101903414-1.0.0.dist-info/RECORD
