Metadata-Version: 2.1
Name: Topsis-Amrendra-101903414
Version: 1.0.0
Summary: Topsis implementation
Home-page: 
Author: Amrendra Pratap Singh
Author-email: singhamrendrapratap19@gmail.com
License: MIT
Classifier: License :: OSI Approved :: MIT License
Classifier: Programming Language :: Python :: 3.6
Classifier: Programming Language :: Python :: 3.7
Classifier: Programming Language :: Python :: 3.8
Classifier: Programming Language :: Python :: 3.9
License-File: LICENSE
Requires-Dist: pandas
Requires-Dist: numpy
